opus/__init__.py
opus/cli.py
opus/execution.py
opus/opus_logging.py
opus/clouds/__init__.py
opus/clouds/cloud.py
opus/clouds/cloud_providers.py
opus/clouds/kubernetes.py
opus/clouds/slurm.py
opus/common_types/__init__.py
opus/common_types/common.py
opus/frameworks/__init__.py
opus/frameworks/framework_types.py
opus/frameworks/frameworks.py
opus/frameworks/ray.py
opus/jobs/__init__.py
opus/jobs/job.py
opus/rayjobs/__init__.py
opus/rayjobs/rayjob.py
opus/templates/kubernetes-ray-template.yaml.j2
opus/templates/slurm-ray-template.sh.j2
opus/utils/__init__.py
opus/utils/common_utils.py
opus/utils/db_utils.py
opus/utils/schema_utils.py
opus/utils/validator_utils.py
pj_opus-0.0.4.dist-info/LICENSE
pj_opus-0.0.4.dist-info/METADATA
pj_opus-0.0.4.dist-info/WHEEL
pj_opus-0.0.4.dist-info/entry_points.txt
pj_opus-0.0.4.dist-info/top_level.txt
pj_opus-0.0.4.dist-info/RECORD
