Metadata-Version: 2.1
Name: pj-opus
Version: 0.0.4
Summary: Opus: An auto-launcher for ray clusters on clouds
Author: AST
Author-email: zhuzhihao@pjlab.org.cn
License: Apache 2.0
Classifier: Programming Language :: Python :: 3.8
Classifier: Programming Language :: Python :: 3.9
Classifier: Programming Language :: Python :: 3.10
Classifier: Programming Language :: Python :: 3.11
Requires-Python: >=3.8, <3.12
License-File: LICENSE
Requires-Dist: wheel
Requires-Dist: click >=7.0
Requires-Dist: pytest ==7.4.3
Requires-Dist: prettytable
Requires-Dist: schema ==0.7.5
Requires-Dist: jinja2
Requires-Dist: pyyaml !=5.4.*,>3.13
Requires-Dist: ray[default]
Requires-Dist: pydantic <2.0,>=1.10.8
Requires-Dist: pendulum ==2.1.2
Requires-Dist: requests ==2.31.0
Requires-Dist: paramiko ==3.3.1
Requires-Dist: colorama
Requires-Dist: kubernetes >=20.13.0
